pynfe/__init__.py
pynfe/excecoes.py
pynfe/data/ISSQN/Lista-Servicos.txt
pynfe/data/MunIBGE/MunIBGE-UF11.txt
pynfe/data/MunIBGE/MunIBGE-UF12.txt
pynfe/data/MunIBGE/MunIBGE-UF13.txt
pynfe/data/MunIBGE/MunIBGE-UF14.txt
pynfe/data/MunIBGE/MunIBGE-UF15.txt
pynfe/data/MunIBGE/MunIBGE-UF16.txt
pynfe/data/MunIBGE/MunIBGE-UF17.txt
pynfe/data/MunIBGE/MunIBGE-UF21.txt
pynfe/data/MunIBGE/MunIBGE-UF22.txt
pynfe/data/MunIBGE/MunIBGE-UF23.txt
pynfe/data/MunIBGE/MunIBGE-UF24.txt
pynfe/data/MunIBGE/MunIBGE-UF25.txt
pynfe/data/MunIBGE/MunIBGE-UF26.txt
pynfe/data/MunIBGE/MunIBGE-UF27.txt
pynfe/data/MunIBGE/MunIBGE-UF28.txt
pynfe/data/MunIBGE/MunIBGE-UF29.txt
pynfe/data/MunIBGE/MunIBGE-UF31.txt
pynfe/data/MunIBGE/MunIBGE-UF32.txt
pynfe/data/MunIBGE/MunIBGE-UF33.txt
pynfe/data/MunIBGE/MunIBGE-UF35.txt
pynfe/data/MunIBGE/MunIBGE-UF41.txt
pynfe/data/MunIBGE/MunIBGE-UF42.txt
pynfe/data/MunIBGE/MunIBGE-UF43.txt
pynfe/data/MunIBGE/MunIBGE-UF50.txt
pynfe/data/MunIBGE/MunIBGE-UF51.txt
pynfe/data/MunIBGE/MunIBGE-UF52.txt
pynfe/data/MunIBGE/MunIBGE-UF53.txt
pynfe/data/MunIBGE/MunIBGE-UF99.txt
pynfe/data/MunIBGE/PaisIBGE.txt
pynfe/entidades/__init__.py
pynfe/entidades/base.py
pynfe/entidades/certificado.py
pynfe/entidades/cliente.py
pynfe/entidades/emitente.py
pynfe/entidades/evento.py
pynfe/entidades/fonte_dados.py
pynfe/entidades/lotes.py
pynfe/entidades/manifesto.py
pynfe/entidades/notafiscal.py
pynfe/entidades/produto.py
pynfe/entidades/servico.py
pynfe/entidades/transportadora.py
pynfe/processamento/__init__.py
pynfe/processamento/assinatura.py
pynfe/processamento/autorizador_nfse.py
pynfe/processamento/comunicacao.py
pynfe/processamento/danfe.py
pynfe/processamento/resposta.py
pynfe/processamento/serializacao.py
pynfe/processamento/validacao.py
pynfe/utils/__init__.py
pynfe/utils/bar_code_128.py
pynfe/utils/descompactar.py
pynfe/utils/flags.py
pynfe/utils/https_nfse.py
pynfe/utils/webservices.py
pynfe/utils/xml_writer.py
pynfe/utils/nfse/__init__.py
pynfe/utils/nfse/betha/__init__.py
pynfe-0.6.0.dist-info/licenses/AUTHORS
pynfe-0.6.0.dist-info/licenses/LICENSE
pynfe-0.6.0.dist-info/METADATA
pynfe-0.6.0.dist-info/WHEEL
pynfe-0.6.0.dist-info/top_level.txt
pynfe-0.6.0.dist-info/RECORD
