Metadata-Version: 2.4
Name: PyNFe
Version: 0.6.0
Summary: Interface library with the Brazilian Electronic Invoice web services
Home-page: https://github.com/TadaSoftware/PyNFe
Author: TadaSoftware
Author-email: tadasoftware@gmail.com
Project-URL: Bug Tracker, https://github.com/TadaSoftware/PyNFe/issues
Project-URL: Wiki, https://github.com/TadaSoftware/PyNFe/wiki
Project-URL: Discussions, https://github.com/TadaSoftware/PyNFe/discussions
Classifier: Programming Language :: Python :: 3
Classifier: License :: OSI Approved :: GNU Lesser General Public License v3 (LGPLv3)
Classifier: Topic :: Software Development :: Libraries
Classifier: Topic :: Software Development :: Libraries :: Python Modules
Classifier: Operating System :: OS Independent
Requires-Python: >=3.8
License-File: LICENSE
License-File: AUTHORS
Requires-Dist: pyopenssl>=23.0.0
Requires-Dist: requests
Requires-Dist: lxml
Requires-Dist: signxml
Provides-Extra: nfse
Requires-Dist: suds-community; extra == "nfse"
Requires-Dist: PyXB-X==1.2.6.3; extra == "nfse"
Provides-Extra: impressao
Requires-Dist: brazilfiscalreport[damdfe]; extra == "impressao"
Dynamic: author
Dynamic: author-email
Dynamic: classifier
Dynamic: description
Dynamic: description-content-type
Dynamic: home-page
Dynamic: license-file
Dynamic: project-url
Dynamic: provides-extra
Dynamic: requires-dist
Dynamic: requires-python
Dynamic: summary
